setup.py
salure_helpers/sqlserver/__init__.py
salure_helpers/sqlserver/sqlserver.py
salure_helpers_sqlserver.egg-info/PKG-INFO
salure_helpers_sqlserver.egg-info/SOURCES.txt
salure_helpers_sqlserver.egg-info/dependency_links.txt
salure_helpers_sqlserver.egg-info/not-zip-safe
salure_helpers_sqlserver.egg-info/requires.txt
salure_helpers_sqlserver.egg-info/top_level.txt