Metadata-Version: 1.0
Name: salure-helpers-sqlserver
Version: 1.0.0
Summary: SQL Server wrapper from Salure
Home-page: UNKNOWN
Author: D&A Salure
Author-email: support@salureconnnect.com
License: Salure License
Platform: UNKNOWN
